xyz_dailylog/__init__.py
xyz_dailylog/admin.py
xyz_dailylog/apis.py
xyz_dailylog/apps.py
xyz_dailylog/cron.py
xyz_dailylog/helper.py
xyz_dailylog/mixins.py
xyz_dailylog/models.py
xyz_dailylog/serializers.py
xyz_dailylog/signals.py
xyz_dailylog/stats.py
xyz_dailylog/stores.py
xyz_dailylog/migrations/0001_initial.py
xyz_dailylog/migrations/0002_auto_20201015_1111.py
xyz_dailylog/migrations/0003_auto_20221021_0724.py
xyz_dailylog/migrations/__init__.py
xyz_dailylog-0.3.3.dist-info/METADATA
xyz_dailylog-0.3.3.dist-info/WHEEL
xyz_dailylog-0.3.3.dist-info/top_level.txt
xyz_dailylog-0.3.3.dist-info/RECORD
