Metadata-Version: 2.1
Name: xyz-dailylog
Version: 0.3.3
Summary: dailylog
Home-page: https://github.com/szuprefix/py-xyz-dailylog
Author: szuprefix
Author-email: szuprefix@126.com
License: MIT
Classifier: Environment :: Web Environment
Classifier: Intended Audience :: Developers
Classifier: Operating System :: OS Independent
Classifier: Topic :: Text Processing :: Indexing
Classifier: Topic :: Utilities
Classifier: Topic :: Internet
Classifier: Topic :: Software Development :: Libraries :: Python Modules
Classifier: Programming Language :: Python
Classifier: Programming Language :: Python :: 2
Classifier: Programming Language :: Python :: 2.7
Classifier: Programming Language :: Python :: 3
Classifier: Programming Language :: Python :: 3.5
Classifier: Programming Language :: Python :: 3.6
Classifier: Programming Language :: Python :: 3.7
Classifier: Programming Language :: Python :: 3.8
Requires-Dist: django>=1.11.2
Requires-Dist: xyz-restful>=0.0.6
Requires-Dist: xyz-util>=0.0.7
Requires-Dist: pymongo
